cryptowrapper.py
xnr_cryptowrapper-0.1.1.dist-info/METADATA
xnr_cryptowrapper-0.1.1.dist-info/WHEEL
xnr_cryptowrapper-0.1.1.dist-info/top_level.txt
xnr_cryptowrapper-0.1.1.dist-info/RECORD
