Metadata-Version: 2.1
Name: xnr-cryptowrapper
Version: 0.1.1
Summary: Wrapper around Cryptocurrency related APIs
Home-page: https://github.com/xnr-k/cryptowrapper
Author: xnr-k
Author-email: xnr.k@protonmail.com
License: UNKNOWN
Platform: UNKNOWN
Classifier: Programming Language :: Python :: 3.6
Classifier: Programming Language :: Python :: 3.7
Requires-Dist: requests (>=2.22.0)
Requires-Dist: requests-async (>=0.6.2)
Requires-Dist: requests-cache (>=0.5.2)
